health_graph/Interpolation.py
health_graph/__init__.py
health_graph/regression.py
health_graph-0.0.5.dist-info/LICENSE
health_graph-0.0.5.dist-info/METADATA
health_graph-0.0.5.dist-info/WHEEL
health_graph-0.0.5.dist-info/top_level.txt
health_graph-0.0.5.dist-info/RECORD
