Metadata-Version: 2.1
Name: health_graph
Version: 0.0.5
Summary: health check tool
Author-email: hwatanabe <hwatanabe@sciencepark.co.jp>
Project-URL: Homepage, https://pypi.org/project/health-graph/
Classifier: Programming Language :: Python :: 3
Classifier: License :: OSI Approved :: MIT License
Classifier: Operating System :: OS Independent
Requires-Python: >=3.8
License-File: LICENSE
